rtx_stone/__init__.py
rtx_stone/diagnostic.py
rtx_stone-2.10.0a0.dist-info/licenses/LICENSE
rtx_stone-2.10.0a0.dist-info/METADATA
rtx_stone-2.10.0a0.dist-info/WHEEL
rtx_stone-2.10.0a0.dist-info/entry_points.txt
rtx_stone-2.10.0a0.dist-info/top_level.txt
rtx_stone-2.10.0a0.dist-info/RECORD
