Metadata-Version: 2.4
Name: rtx-stone
Version: 2.10.0a0
Summary: PyTorch 2.10 with native SM 12.0 (Blackwell) support for NVIDIA RTX 50-series GPUs on Windows
Author: RTX-STone Contributors
Maintainer: RTX-STone Contributors
License: BSD-3-Clause
Project-URL: Homepage, https://github.com/kentstone84/pytorch-rtx5080-support
Project-URL: Documentation, https://github.com/kentstone84/pytorch-rtx5080-support#readme
Project-URL: Repository, https://github.com/kentstone84/pytorch-rtx5080-support
Project-URL: Issues, https://github.com/kentstone84/pytorch-rtx5080-support/issues
Project-URL: Changelog, https://github.com/kentstone84/pytorch-rtx5080-support/blob/main/CHANGELOG.md
Keywords: pytorch,rtx,rtx-5080,rtx-5090,rtx-50-series,blackwell,sm-12.0,cuda,triton,deep-learning,machine-learning,gpu,nvidia,windows,flash-attention,llm,optimization
Classifier: Development Status :: 4 - Beta
Classifier: Intended Audience :: Developers
Classifier: Intended Audience :: Science/Research
Classifier: License :: OSI Approved :: BSD License
Classifier: Programming Language :: Python :: 3
Classifier: Programming Language :: Python :: 3.10
Classifier: Programming Language :: Python :: 3.11
Classifier: Topic :: Scientific/Engineering :: Artificial Intelligence
Classifier: Topic :: Software Development :: Libraries :: Python Modules
Classifier: Operating System :: Microsoft :: Windows
Classifier: Environment :: GPU :: NVIDIA CUDA
Requires-Python: <3.12,>=3.10
License-File: LICENSE
Requires-Dist: filelock
Requires-Dist: fsspec
Requires-Dist: Jinja2
Requires-Dist: MarkupSafe
Requires-Dist: mpmath
Requires-Dist: networkx
Requires-Dist: sympy
Requires-Dist: typing-extensions>=4.10.0
Requires-Dist: numpy>=1.24.0
Requires-Dist: pillow>=10.0.0
Requires-Dist: tqdm>=4.65.0
Provides-Extra: triton
Requires-Dist: triton-windows<3.6; extra == "triton"
Provides-Extra: huggingface
Requires-Dist: transformers>=4.35.0; extra == "huggingface"
Requires-Dist: accelerate>=0.24.0; extra == "huggingface"
Requires-Dist: safetensors>=0.4.0; extra == "huggingface"
Requires-Dist: sentencepiece>=0.1.99; extra == "huggingface"
Requires-Dist: tokenizers>=0.15.0; extra == "huggingface"
Provides-Extra: quantization
Requires-Dist: bitsandbytes>=0.41.0; extra == "quantization"
Provides-Extra: image-generation
Requires-Dist: diffusers>=0.24.0; extra == "image-generation"
Provides-Extra: monitoring
Requires-Dist: psutil>=5.9.0; extra == "monitoring"
Requires-Dist: nvidia-ml-py3>=7.352.0; extra == "monitoring"
Provides-Extra: notebooks
Requires-Dist: jupyter>=1.0.0; extra == "notebooks"
Requires-Dist: ipykernel>=6.25.0; extra == "notebooks"
Requires-Dist: matplotlib>=3.7.0; extra == "notebooks"
Provides-Extra: dev
Requires-Dist: pytest>=7.4.0; extra == "dev"
Requires-Dist: black>=23.0.0; extra == "dev"
Requires-Dist: flake8>=6.0.0; extra == "dev"
Requires-Dist: mypy>=1.0.0; extra == "dev"
Provides-Extra: all
Requires-Dist: rtx-stone[huggingface,image-generation,monitoring,notebooks,quantization,triton]; extra == "all"
Dynamic: license-file
